csup_analyzer-0.1.2.dist-info/METADATA
csup_analyzer-0.1.2.dist-info/WHEEL
csup_analyzer-0.1.2.dist-info/licenses/LICENSE
csup_analyzer/__init__.py
csup_analyzer/event/Driver.py
csup_analyzer/event/Event.py
csup_analyzer/event/LineUp.py
csup_analyzer/event/Result.py
csup_analyzer/event/__init__.py
csup_analyzer/plots/Plots.py
csup_analyzer/plots/__init__.py
csup_analyzer/replay/FileHandler.py
csup_analyzer/replay/ReplayFile.py
csup_analyzer/replay/__init__.py
csup_analyzer-0.1.2.dist-info/RECORD
