Metadata-Version: 2.1
Name: csup_analyzer
Version: 0.1.2
Summary: Reads replay files from the game Circuit Superstars and offers tools to analyze the extracted data
Author-Email: Andre Petersen <info@csup.app>
License: MIT
Requires-Python: >=3.9
Requires-Dist: pandas>=2.0.2
Requires-Dist: numpy>=1.25.0
Requires-Dist: matplotlib>=3.7.1
Requires-Dist: scipy>=1.9.3
